lazyRecursion.py
lazyRecursion-0.1.1.dist-info/LICENCE
lazyRecursion-0.1.1.dist-info/METADATA
lazyRecursion-0.1.1.dist-info/WHEEL
lazyRecursion-0.1.1.dist-info/top_level.txt
lazyRecursion-0.1.1.dist-info/RECORD
