Metadata-Version: 2.1
Name: lazyRecursion
Version: 0.1.1
Summary: lazy RecursiveSequence with optional caching
Home-page: https://github.com/FelixBenning/lazyRecursion
Author: Felix Benning
Author-email: felix.benning@gmail.com
License: UNKNOWN
Platform: UNKNOWN
Classifier: Programming Language :: Python :: 3
Classifier: License :: OSI Approved :: Mozilla Public License 2.0 (MPL 2.0)
Classifier: Development Status :: 4 - Beta
Requires-Python: >=3.8
